workflow_rdf/__init__.py
workflow_rdf/project.py
workflow_rdf/lammps/__init__.py
workflow_rdf/lammps/lammps.py
workflow_rdf/sphinx/__init__.py
workflow_rdf/sphinx/sphinx.py
workflow_rdf-0.0.4.dist-info/LICENSE
workflow_rdf-0.0.4.dist-info/METADATA
workflow_rdf-0.0.4.dist-info/WHEEL
workflow_rdf-0.0.4.dist-info/top_level.txt
workflow_rdf-0.0.4.dist-info/RECORD
