Metadata-Version: 2.1
Name: workflow_rdf
Version: 0.0.4
Summary: pyiron jobs with RDF elements
Home-page: https://pyscal.org
Download-URL: https://github.com/pyscal/workflow_rdf
Author: Abril Azocar Guzman, Sarath Menon
Author-email: sarath.menon@pyscal.org
Classifier: Programming Language :: Python :: 3
License-File: LICENSE
Requires-Dist: numpy
